templify/__init__.py
templify/app.py
templify/main.py
templify/services.py
templify-0.0.16.dist-info/METADATA
templify-0.0.16.dist-info/WHEEL
templify-0.0.16.dist-info/entry_points.txt
templify-0.0.16.dist-info/top_level.txt
templify-0.0.16.dist-info/RECORD
